{
  "cnp": "2910823151959",
  "nume": "CAPATAN LUMINITA",
  "prenume": null,
  "rezultate": [
    {
      "analiza_standard_id": null,
      "denumire_raw": "Trombocite                              280 10^3/ul                        150 - 400 / 10^3/ul",
      "valoare": null,
      "valoare_text": "Leucocite                                   7.47 10^3/ul                         4 - 10 / 10^3/ul",
      "unitate": null,
      "interval_min": null,
      "interval_max": null,
      "flag": null,
      "categorie": "Hemoleucograma",
      "ordine": 0,
      "organism_raw": null,
      "rezultat_tip": null,
      "needs_review": false,
      "review_reasons": [],
      "ocr_confidence": null
    },
    {
      "analiza_standard_id": null,
      "denumire_raw": "Corpi cetonici                                        -                                   - (Negativ)",
      "valoare": null,
      "valoare_text": "Urobilinogen                         NORMAL                              Normal",
      "unitate": null,
      "interval_min": null,
      "interval_max": null,
      "flag": null,
      "categorie": "Examen urina",
      "ordine": 1,
      "organism_raw": null,
      "rezultat_tip": null,
      "needs_review": false,
      "review_reasons": [],
      "ocr_confidence": null
    },
    {
      "analiza_standard_id": null,
      "denumire_raw": "Bilirubina                                            -                                   - (Negativ)",
      "valoare": null,
      "valoare_text": "Leucocite                                 25 Leu/ul                                - (Negativ)",
      "unitate": null,
      "interval_min": null,
      "interval_max": null,
      "flag": null,
      "categorie": "Examen urina",
      "ordine": 2,
      "organism_raw": null,
      "rezultat_tip": null,
      "needs_review": false,
      "review_reasons": [],
      "ocr_confidence": null
    },
    {
      "analiza_standard_id": null,
      "denumire_raw": "Celule epiteliale",
      "valoare": null,
      "valoare_text": "Leucocite                                      Relativ frecvente                      Rare (1-4/camp 40 X)",
      "unitate": null,
      "interval_min": null,
      "interval_max": null,
      "flag": null,
      "categorie": "Examen urina",
      "ordine": 3,
      "organism_raw": null,
      "rezultat_tip": null,
      "needs_review": false,
      "review_reasons": [],
      "ocr_confidence": null
    },
    {
      "analiza_standard_id": null,
      "denumire_raw": "Trombocite 280 10^3/ul 150 - 400 / 10^3/ul",
      "valoare": null,
      "valoare_text": "Leucocite 7.47 10^3/ul 4 - 10 / 10^3/ul",
      "unitate": null,
      "interval_min": null,
      "interval_max": null,
      "flag": null,
      "categorie": "Hemoleucograma",
      "ordine": 4,
      "organism_raw": null,
      "rezultat_tip": null,
      "needs_review": false,
      "review_reasons": [],
      "ocr_confidence": null
    },
    {
      "analiza_standard_id": null,
      "denumire_raw": "Corpi cetonici - - (Negativ)",
      "valoare": null,
      "valoare_text": "Urobilinogen NORMAL Normal",
      "unitate": null,
      "interval_min": null,
      "interval_max": null,
      "flag": null,
      "categorie": "Examen urina",
      "ordine": 5,
      "organism_raw": null,
      "rezultat_tip": null,
      "needs_review": false,
      "review_reasons": [],
      "ocr_confidence": null
    },
    {
      "analiza_standard_id": null,
      "denumire_raw": "Bilirubina - - (Negativ)",
      "valoare": null,
      "valoare_text": "Leucocite 25 Leu/ul - (Negativ)",
      "unitate": null,
      "interval_min": null,
      "interval_max": null,
      "flag": null,
      "categorie": "Examen urina",
      "ordine": 6,
      "organism_raw": null,
      "rezultat_tip": null,
      "needs_review": false,
      "review_reasons": [],
      "ocr_confidence": null
    },
    {
      "analiza_standard_id": null,
      "denumire_raw": "Celule epiteliale",
      "valoare": null,
      "valoare_text": "Leucocite Relativ frecvente Rare (1-4/camp 40 X)",
      "unitate": null,
      "interval_min": null,
      "interval_max": null,
      "flag": null,
      "categorie": "Examen urina",
      "ordine": 7,
      "organism_raw": null,
      "rezultat_tip": null,
      "needs_review": false,
      "review_reasons": [],
      "ocr_confidence": null
    },
    {
      "analiza_standard_id": null,
      "denumire_raw": "VSH -Sange - Metoda Westergreen",
      "valoare": 13.0,
      "valoare_text": null,
      "unitate": "mm/h",
      "interval_min": 0.0,
      "interval_max": 20.0,
      "flag": null,
      "categorie": "Hemoleucograma",
      "ordine": 8,
      "organism_raw": null,
      "rezultat_tip": null,
      "needs_review": false,
      "review_reasons": [],
      "ocr_confidence": null
    },
    {
      "analiza_standard_id": null,
      "denumire_raw": "Hemoglobina",
      "valoare": 14.5,
      "valoare_text": null,
      "unitate": "g/dl",
      "interval_min": 11.8,
      "interval_max": 15.2,
      "flag": null,
      "categorie": "Hemoleucograma",
      "ordine": 9,
      "organism_raw": null,
      "rezultat_tip": null,
      "needs_review": false,
      "review_reasons": [],
      "ocr_confidence": null
    },
    {
      "analiza_standard_id": null,
      "denumire_raw": "Hematocrit",
      "valoare": 43.6,
      "valoare_text": null,
      "unitate": "%",
      "interval_min": 37.0,
      "interval_max": 46.0,
      "flag": null,
      "categorie": "Hemoleucograma",
      "ordine": 10,
      "organism_raw": null,
      "rezultat_tip": null,
      "needs_review": false,
      "review_reasons": [],
      "ocr_confidence": null
    },
    {
      "analiza_standard_id": null,
      "denumire_raw": "Trombocite",
      "valoare": 280.0,
      "valoare_text": null,
      "unitate": "10^3/ul",
      "interval_min": 150.0,
      "interval_max": 400.0,
      "flag": null,
      "categorie": "Hemoleucograma",
      "ordine": 11,
      "organism_raw": null,
      "rezultat_tip": null,
      "needs_review": false,
      "review_reasons": [],
      "ocr_confidence": null
    },
    {
      "analiza_standard_id": null,
      "denumire_raw": "Leucocite",
      "valoare": 7.47,
      "valoare_text": null,
      "unitate": "10^3/ul",
      "interval_min": 4.0,
      "interval_max": 10.0,
      "flag": null,
      "categorie": "Hemoleucograma",
      "ordine": 12,
      "organism_raw": null,
      "rezultat_tip": null,
      "needs_review": false,
      "review_reasons": [],
      "ocr_confidence": null
    },
    {
      "analiza_standard_id": null,
      "denumire_raw": "Neutrofile %",
      "valoare": 63.8,
      "valoare_text": null,
      "unitate": "%",
      "interval_min": 45.0,
      "interval_max": 80.0,
      "flag": null,
      "categorie": "Hemoleucograma",
      "ordine": 13,
      "organism_raw": null,
      "rezultat_tip": null,
      "needs_review": false,
      "review_reasons": [],
      "ocr_confidence": null
    },
    {
      "analiza_standard_id": null,
      "denumire_raw": "Neutrofile",
      "valoare": 4.76,
      "valoare_text": null,
      "unitate": "10^3/ul",
      "interval_min": 2.0,
      "interval_max": 8.0,
      "flag": null,
      "categorie": "Hemoleucograma",
      "ordine": 14,
      "organism_raw": null,
      "rezultat_tip": null,
      "needs_review": false,
      "review_reasons": [],
      "ocr_confidence": null
    },
    {
      "analiza_standard_id": null,
      "denumire_raw": "Eozinofile %",
      "valoare": 0.4,
      "valoare_text": null,
      "unitate": "%",
      "interval_min": 0.0,
      "interval_max": 7.0,
      "flag": null,
      "categorie": "Hemoleucograma",
      "ordine": 15,
      "organism_raw": null,
      "rezultat_tip": null,
      "needs_review": false,
      "review_reasons": [],
      "ocr_confidence": null
    },
    {
      "analiza_standard_id": null,
      "denumire_raw": "Eozinofile",
      "valoare": 0.03,
      "valoare_text": null,
      "unitate": "10^3/ul",
      "interval_min": 0.05,
      "interval_max": 0.7,
      "flag": "L",
      "categorie": "Hemoleucograma",
      "ordine": 16,
      "organism_raw": null,
      "rezultat_tip": null,
      "needs_review": false,
      "review_reasons": [],
      "ocr_confidence": null
    },
    {
      "analiza_standard_id": null,
      "denumire_raw": "Bazofile %",
      "valoare": 0.1,
      "valoare_text": null,
      "unitate": "%",
      "interval_min": 0.0,
      "interval_max": 2.0,
      "flag": null,
      "categorie": "Hemoleucograma",
      "ordine": 17,
      "organism_raw": null,
      "rezultat_tip": null,
      "needs_review": false,
      "review_reasons": [],
      "ocr_confidence": null
    },
    {
      "analiza_standard_id": null,
      "denumire_raw": "Bazofile",
      "valoare": 0.01,
      "valoare_text": null,
      "unitate": "10^3/ul",
      "interval_min": 0.0,
      "interval_max": 0.2,
      "flag": null,
      "categorie": "Hemoleucograma",
      "ordine": 18,
      "organism_raw": null,
      "rezultat_tip": null,
      "needs_review": false,
      "review_reasons": [],
      "ocr_confidence": null
    },
    {
      "analiza_standard_id": null,
      "denumire_raw": "Limfocite %",
      "valoare": 28.9,
      "valoare_text": null,
      "unitate": "%",
      "interval_min": 25.0,
      "interval_max": 40.0,
      "flag": null,
      "categorie": "Hemoleucograma",
      "ordine": 19,
      "organism_raw": null,
      "rezultat_tip": null,
      "needs_review": false,
      "review_reasons": [],
      "ocr_confidence": null
    },
    {
      "analiza_standard_id": null,
      "denumire_raw": "Limfocite",
      "valoare": 2.16,
      "valoare_text": null,
      "unitate": "10^3/ul",
      "interval_min": 1.0,
      "interval_max": 4.0,
      "flag": null,
      "categorie": "Hemoleucograma",
      "ordine": 20,
      "organism_raw": null,
      "rezultat_tip": null,
      "needs_review": false,
      "review_reasons": [],
      "ocr_confidence": null
    },
    {
      "analiza_standard_id": null,
      "denumire_raw": "Monocite %",
      "valoare": 6.8,
      "valoare_text": null,
      "unitate": "%",
      "interval_min": 0.0,
      "interval_max": 15.0,
      "flag": null,
      "categorie": "Hemoleucograma",
      "ordine": 21,
      "organism_raw": null,
      "rezultat_tip": null,
      "needs_review": false,
      "review_reasons": [],
      "ocr_confidence": null
    },
    {
      "analiza_standard_id": null,
      "denumire_raw": "Monocite",
      "valoare": 0.51,
      "valoare_text": null,
      "unitate": "10^3/ul",
      "interval_min": 0.3,
      "interval_max": 1.0,
      "flag": null,
      "categorie": "Hemoleucograma",
      "ordine": 22,
      "organism_raw": null,
      "rezultat_tip": null,
      "needs_review": false,
      "review_reasons": [],
      "ocr_confidence": null
    },
    {
      "analiza_standard_id": null,
      "denumire_raw": "VEM",
      "valoare": 97.8,
      "valoare_text": null,
      "unitate": "FL",
      "interval_min": 82.5,
      "interval_max": 97.4,
      "flag": "H",
      "categorie": "Hemoleucograma",
      "ordine": 23,
      "organism_raw": null,
      "rezultat_tip": null,
      "needs_review": false,
      "review_reasons": [],
      "ocr_confidence": null
    },
    {
      "analiza_standard_id": null,
      "denumire_raw": "HEM",
      "valoare": 32.5,
      "valoare_text": null,
      "unitate": "pg",
      "interval_min": 27.0,
      "interval_max": 34.0,
      "flag": null,
      "categorie": "Hemoleucograma",
      "ordine": 24,
      "organism_raw": null,
      "rezultat_tip": null,
      "needs_review": false,
      "review_reasons": [],
      "ocr_confidence": null
    },
    {
      "analiza_standard_id": null,
      "denumire_raw": "CHEM",
      "valoare": 33.3,
      "valoare_text": null,
      "unitate": "g/dl",
      "interval_min": 32.0,
      "interval_max": 36.0,
      "flag": null,
      "categorie": "Hemoleucograma",
      "ordine": 25,
      "organism_raw": null,
      "rezultat_tip": null,
      "needs_review": false,
      "review_reasons": [],
      "ocr_confidence": null
    },
    {
      "analiza_standard_id": null,
      "denumire_raw": "MPV",
      "valoare": 11.5,
      "valoare_text": null,
      "unitate": "FL",
      "interval_min": 8.0,
      "interval_max": 13.0,
      "flag": null,
      "categorie": "Hemoleucograma",
      "ordine": 26,
      "organism_raw": null,
      "rezultat_tip": null,
      "needs_review": false,
      "review_reasons": [],
      "ocr_confidence": null
    },
    {
      "analiza_standard_id": null,
      "denumire_raw": "RDW",
      "valoare": 12.3,
      "valoare_text": null,
      "unitate": "%",
      "interval_min": 11.0,
      "interval_max": 16.0,
      "flag": null,
      "categorie": "Hemoleucograma",
      "ordine": 27,
      "organism_raw": null,
      "rezultat_tip": null,
      "needs_review": false,
      "review_reasons": [],
      "ocr_confidence": null
    },
    {
      "analiza_standard_id": null,
      "denumire_raw": "Fosfataza alcalina -Ser - Spectrofotometrie (Advia 1800)",
      "valoare": 51.32,
      "valoare_text": null,
      "unitate": "U/L",
      "interval_min": 35.0,
      "interval_max": 104.0,
      "flag": "L",
      "categorie": "Biochimie",
      "ordine": 28,
      "organism_raw": null,
      "rezultat_tip": null,
      "needs_review": false,
      "review_reasons": [],
      "ocr_confidence": null
    },
    {
      "analiza_standard_id": null,
      "denumire_raw": "Glicemie a jeune -Ser - Spectofotometrie (Advia 1800)",
      "valoare": 94.0,
      "valoare_text": null,
      "unitate": "mg/dL",
      "interval_min": 74.0,
      "interval_max": 106.0,
      "flag": null,
      "categorie": "Biochimie",
      "ordine": 29,
      "organism_raw": null,
      "rezultat_tip": null,
      "needs_review": false,
      "review_reasons": [],
      "ocr_confidence": null
    },
    {
      "analiza_standard_id": null,
      "denumire_raw": "Proteina C reactiva cantitativ -Ser - turbidimetrie (Advia 1800)",
      "valoare": 0.16,
      "valoare_text": null,
      "unitate": "mg/dL",
      "interval_min": 0.0,
      "interval_max": 0.5,
      "flag": null,
      "categorie": "Biochimie",
      "ordine": 30,
      "organism_raw": null,
      "rezultat_tip": null,
      "needs_review": false,
      "review_reasons": [],
      "ocr_confidence": null
    },
    {
      "analiza_standard_id": null,
      "denumire_raw": "Sideremie -Ser - Spectrofotometrie (Advia 1800)",
      "valoare": 127.0,
      "valoare_text": null,
      "unitate": "ug/dl",
      "interval_min": 50.0,
      "interval_max": 170.0,
      "flag": null,
      "categorie": "Biochimie",
      "ordine": 31,
      "organism_raw": null,
      "rezultat_tip": null,
      "needs_review": false,
      "review_reasons": [],
      "ocr_confidence": null
    },
    {
      "analiza_standard_id": null,
      "denumire_raw": "TGO / AST -Ser - Spectrofotometrie (Advia 1800)",
      "valoare": 21.0,
      "valoare_text": null,
      "unitate": "U/L",
      "interval_min": 0.0,
      "interval_max": 32.0,
      "flag": "L",
      "categorie": "Biochimie",
      "ordine": 32,
      "organism_raw": null,
      "rezultat_tip": null,
      "needs_review": false,
      "review_reasons": [],
      "ocr_confidence": null
    },
    {
      "analiza_standard_id": null,
      "denumire_raw": "TGP / ALT -Ser - Spectrofotometrie (Advia 1800)",
      "valoare": 19.0,
      "valoare_text": null,
      "unitate": "U/L",
      "interval_min": 0.0,
      "interval_max": 49.0,
      "flag": "L",
      "categorie": "Biochimie",
      "ordine": 33,
      "organism_raw": null,
      "rezultat_tip": null,
      "needs_review": false,
      "review_reasons": [],
      "ocr_confidence": null
    },
    {
      "analiza_standard_id": null,
      "denumire_raw": "Creatinina serica -Ser -",
      "valoare": 0.8,
      "valoare_text": null,
      "unitate": "mg/dL",
      "interval_min": 0.0,
      "interval_max": 1.02,
      "flag": null,
      "categorie": "Biochimie",
      "ordine": 34,
      "organism_raw": null,
      "rezultat_tip": null,
      "needs_review": false,
      "review_reasons": [],
      "ocr_confidence": null
    },
    {
      "analiza_standard_id": null,
      "denumire_raw": "Rata de filtrare glomerulara(RFG)",
      "valoare": 96.19,
      "valoare_text": null,
      "unitate": "ml/min/1.73",
      "interval_min": 60.0,
      "interval_max": 600.0,
      "flag": null,
      "categorie": "Biochimie",
      "ordine": 35,
      "organism_raw": null,
      "rezultat_tip": null,
      "needs_review": false,
      "review_reasons": [],
      "ocr_confidence": null
    },
    {
      "analiza_standard_id": null,
      "denumire_raw": "Urobilinogen",
      "valoare": null,
      "valoare_text": "NORMAL",
      "unitate": null,
      "interval_min": null,
      "interval_max": null,
      "flag": null,
      "categorie": "Examen urina",
      "ordine": 36,
      "organism_raw": null,
      "rezultat_tip": null,
      "needs_review": false,
      "review_reasons": [],
      "ocr_confidence": null
    },
    {
      "analiza_standard_id": null,
      "denumire_raw": "Leucocite",
      "valoare": 25.0,
      "valoare_text": null,
      "unitate": "Leu/ul",
      "interval_min": null,
      "interval_max": null,
      "flag": null,
      "categorie": "Examen urina",
      "ordine": 37,
      "organism_raw": null,
      "rezultat_tip": null,
      "needs_review": false,
      "review_reasons": [],
      "ocr_confidence": null
    },
    {
      "analiza_standard_id": null,
      "denumire_raw": "Relativ frecvente",
      "valoare": null,
      "valoare_text": "Rare",
      "unitate": null,
      "interval_min": null,
      "interval_max": null,
      "flag": null,
      "categorie": "Examen urina",
      "ordine": 38,
      "organism_raw": null,
      "rezultat_tip": null,
      "needs_review": false,
      "review_reasons": [],
      "ocr_confidence": null
    },
    {
      "analiza_standard_id": null,
      "denumire_raw": "Femei>45 ani-4.9-232.3 ng/ml Barbati: 18.2-",
      "valoare": 341.2,
      "valoare_text": null,
      "unitate": "ng/ml",
      "interval_min": null,
      "interval_max": null,
      "flag": null,
      "categorie": "Imunologie si Serologie",
      "ordine": 39,
      "organism_raw": null,
      "rezultat_tip": null,
      "needs_review": false,
      "review_reasons": [],
      "ocr_confidence": null
    },
    {
      "analiza_standard_id": null,
      "denumire_raw": "Feritina -Ser - Chemiluminiscenta",
      "valoare": 26.91,
      "valoare_text": null,
      "unitate": "ng/ml",
      "interval_min": 7.0,
      "interval_max": 13.0,
      "flag": "H",
      "categorie": "Imunologie si Serologie",
      "ordine": 40,
      "organism_raw": null,
      "rezultat_tip": null,
      "needs_review": false,
      "review_reasons": [],
      "ocr_confidence": null
    },
    {
      "analiza_standard_id": null,
      "denumire_raw": "FT4-Tiroxina serica libera -Ser - Chemiluminiscenta",
      "valoare": 1241.0,
      "valoare_text": null,
      "unitate": "ng/dL",
      "interval_min": 0.8,
      "interval_max": 1.7,
      "flag": "H",
      "categorie": "Imunologie si Serologie",
      "ordine": 41,
      "organism_raw": null,
      "rezultat_tip": null,
      "needs_review": false,
      "review_reasons": [],
      "ocr_confidence": null
    },
    {
      "analiza_standard_id": null,
      "denumire_raw": "TSH-Hormonul hipofizar tireostimulator bazal -Ser -",
      "valoare": 2.36,
      "valoare_text": null,
      "unitate": "uUI/mL",
      "interval_min": 0.3,
      "interval_max": 3.6,
      "flag": null,
      "categorie": "Imunologie si Serologie",
      "ordine": 42,
      "organism_raw": null,
      "rezultat_tip": null,
      "needs_review": false,
      "review_reasons": [],
      "ocr_confidence": null
    },
    {
      "analiza_standard_id": null,
      "denumire_raw": "Chemiluminiscenta #Vitamina B12 -Ser -",
      "valoare": 190.0,
      "valoare_text": null,
      "unitate": "pg/mL",
      "interval_min": 197.0,
      "interval_max": 771.0,
      "flag": "L",
      "categorie": "Imunologie si Serologie",
      "ordine": 43,
      "organism_raw": null,
      "rezultat_tip": null,
      "needs_review": false,
      "review_reasons": [],
      "ocr_confidence": null
    }
  ]
}